{"verbose_level":1,"base_dir":"/scratch/workspace/runtime-uk.ac.diamond.dawn.product/Ptycho/src","experiment":{"data":{"data_dir":"Data","data_ID":"24978","data_file":"merlin-24978.hdf","sourcetype":"static"},"source":{"energy":10000,"lam":-1,"flux":100000000},"detector":{"name":"merlin","distance":14.138,"pix_pitch":[55e-6,55e-6],"N":[515,515],"mask":"MASKPATH"},"scan":{"path":"/scratch/workspace/runtime-uk.ac.diamond.dawn.product/Ptycho/src/Data/24978.nxs","load_flag":1,"rotation":0,"orientation":"00","scale":[1,1],"type":"Snake","dR":[3E-07,3E-07],"offset":[0.4,0.4],"N":[10,10],"positions":[]},"probe":{"convergence":0,"aperture_type":"circ","aperture_size":0.00001,"focal_dist":-1,"distance":0.0001},"object":{"name":"Siemens Star"}},"process":{"plot_interval":1,"save_interval":-1,"save_dir":"ReconstructionFiles/","save_file":"EXPERIMENTID_DATETIME.h5","data_type":"single","common":{"source":{"energy":10000,"wav":"","lam":-1,"flux":100000000},"detector":{"name":"merlin","orientation":"00","rotation":0,"distance":14.138,"centre":[211,223],"bin":[1,1],"crop":[256,256],"pix_pitch":[0.000055,0.000055],"N":[515,515],"mask":"MASKPATH"},"scan":{"path":"/scratch/workspace/runtime-uk.ac.diamond.dawn.product/Ptycho/src/Data/24978.nxs","load_flag":1,"rotation":0,"orientation":"00","scale":[1,1],"type":"Snake","dR":[3e-7,3e-7],"N":[10,10],"offset":[0.4,0.4],"positions":[]},"probe":{"path":"PROBEPATH","load_flag":0,"convergence":0,"aperture_type":"circ","aperture_size":0.00001,"focal_dist":-1,"distance":0},"object":{"name":"Siemens Star","path":"OBJECTPATH","load_flag":0,"type":"freespace"}},"PIE":{"name":"PIE","iterations":10,"order":1,"probe":{"alpha":1,"start":1,"end":-1},"object":{"alpha":1,"start":2,"end":-1},"detector":{"border":[0,0],"upsample":[1,1]},"scan":{"start":-1,"end":-1,"maximum radius":0.000001,"trials":1,"positions":""}},"DM":{"name":"DM","iterations":100,"order":2,"probe":{"alpha":"","start":"","end":""},"object":{"alpha":"","start":"","end":""}},"ML":{"name":"ML","iterations":50,"order":3,"probe":{"alpha":"","start":"","end":""},"object":{"alpha":"","start":"","end":""}},"output":{"probe":[],"object":[],"scan":[],"error":""},"interaction":{"primary_address":"tcp://127.0.0.2","primary_port":5570,"port_range":"5571:5580"}}}