{"verbose_level":1,"data_type":"single","io":{"base_dir":"/data/CDI/simulations/ptypy/","run":"None","data_dir":"analysis/","plot_dir":"plots/%(run)s/","plot_file":"%(run)s_%(algorithm)s_%(it)04d.png","plot_interval":2,"save_dir":"recons/%(run)s/","save_file":"%(run)s_%(algorithm)s_%(it)04d.h5","dump_dir":"dumps/%(run)s/","dump_file":"%(run)s_%(algorithm)s_%(it)04d.h5"},"model":{"source":"None","tags":"file","geometry":{"energy":7.2,"lam":"","z":7.19,"psize_det":172e-6,"psize_sam":"","N":220,"prop_type":"farfield"},"xy":{"scan_type":"None","dr":0.3e-6,"nr":10,"nth":5,"lx":3e-6,"ly":3e-6,"nx":10,"ny":10,"dx":1e-6,"dy":1e-6,"positions":"None"},"illumination":{"probe_type":"parallel","incoming":"None","phase_noise_rms":0.0,"phase_noise_mfs":2.0,"aperture_type":"circ","aperture_size":"","aperture_edge":2,"focal_dist":"","prop_dist":0.0001,"UseConjugate":"False","antialiasing":2.0,"spot_size":"","photons":1e8,"probe":""},"sample":{"source":"diffraction","offset":"(0,0)","zoom":1.0,"formula":"None","density":1.0,"thickness":1e-6,"ref_index":0.5+0.j,"smoothing_mfs":2,"noise_rms":"","noise_mfs":10,"fill":1.0+0.j,"obj":""},"coherence":{"Nprobe_modes":1,"Nobject_modes":1,"energies":[1.0]},"sharing":{"scan_per_probe":1,"scan_per_object":1,"object_shared_with":"None","object_share_power":1,"probe_shared_with":"None","probe_share_power":1}},"scans":"","data":{"file":"","sourcetype":"static"},"interaction":{"primary_address":"tcp://127.0.0.2","primary_port":5570,"port_range":"5571:5580"},"engine":{"common":{"numiter":2000,"numiter_contiguous":1,"probe_support":0.7,"probe_inertia":0.001,"object_inertia":0.1,"obj_smooth_std":20,"clip_object":"None"},"DM":{"name":"DM","alpha":1,"probe_update_start":2,"update_object_first":"True","overlap_converge_factor":0.05,"overlap_max_iterations":10,"fourier_relax_factor":0.01},"ML":{"name":"ML","ML_type":"gaussian","floating_intensities":"False","intensity_renormalization":1.,"reg_del2":"True","reg_del2_amplitude":.01,"smooth_gradient":0,"scale_precond":"False","scale_probe_object":1.,"probe_update_start":0}},"engines":"","simulation":{"rebin":1,"antialiasing":2,"position_noise":1e-10}}